fastchargeapi_cli/__generated__/__init__.py
fastchargeapi_cli/__generated__/gql_operations.py
fastchargeapi_cli/__init__.py
fastchargeapi_cli/account.py
fastchargeapi_cli/auth_file.py
fastchargeapi_cli/config.py
fastchargeapi_cli/context_obj.py
fastchargeapi_cli/exceptions.py
fastchargeapi_cli/fastapi_account.py
fastchargeapi_cli/fastapi_api.py
fastchargeapi_cli/fastapi_subscription.py
fastchargeapi_cli/fastcharge_account.py
fastchargeapi_cli/fastcharge_api.py
fastchargeapi_cli/fastcharge_app.py
fastchargeapi_cli/fastcharge_pricing.py
fastchargeapi_cli/fastcharge_stripe.py
fastchargeapi_cli/graphql_client.py
fastchargeapi_cli/groups.py
fastchargeapi_cli/http.py
fastchargeapi_cli/local_server.py
fastchargeapi_cli/login.py
fastchargeapi_cli/main.py
fastchargeapi_cli/operations.graphql
fastchargeapi_cli/remote_secret.py
fastchargeapi_cli/token.py
fastchargeapi_cli/version.py
fastchargeapi_cli-1.0.7.dist-info/LICENSE
fastchargeapi_cli-1.0.7.dist-info/LICENSE.txt
fastchargeapi_cli-1.0.7.dist-info/METADATA
fastchargeapi_cli-1.0.7.dist-info/WHEEL
fastchargeapi_cli-1.0.7.dist-info/entry_points.txt
fastchargeapi_cli-1.0.7.dist-info/RECORD
