Metadata-Version: 2.1
Name: fastchargeapi-cli
Version: 1.0.7
Summary: Official CLI for managing apps and account on FastchargeAPI.com
Home-page: https://fastchargeapi.com
License: GNU v3.0
Author: FastchargeAPI
Author-email: fastchargeapi@gmail.com
Requires-Python: >=3.9,<4.0
Classifier: License :: Other/Proprietary License
Classifier: Programming Language :: Python :: 3
Classifier: Programming Language :: Python :: 3.9
Classifier: Programming Language :: Python :: 3.10
Classifier: Programming Language :: Python :: 3.11
Requires-Dist: aws-requests-auth (>=0.4.3,<0.5.0)
Requires-Dist: blessings (>=1.7,<2.0)
Requires-Dist: boto3 (>=1.26.144,<2.0.0)
Requires-Dist: click (>=8.1.3,<9.0.0)
Requires-Dist: click-aliases (>=1.0.1,<2.0.0)
Requires-Dist: colorama (>=0.4.6,<0.5.0)
Requires-Dist: emoji (>=2.2.0,<3.0.0)
Requires-Dist: flask-cors (>=3.0.10,<4.0.0)
Requires-Dist: gql[all] (>=3.4.0,<4.0.0)
Requires-Dist: packaging (>=23.1,<24.0)
Requires-Dist: pydantic (>=1.10.8,<2.0.0)
Requires-Dist: pyjwt[crypto] (>=2.6.0,<3.0.0)
Requires-Dist: python-jose[cryptography] (>=3.3.0,<4.0.0)
Requires-Dist: sgqlc (>=16.1,<17.0)
Requires-Dist: tomli (>=2.0.1,<3.0.0)
Project-URL: Repository, https://github.com/FastchargeAPI/fastchargeapi-cli
